Metadata-Version: 2.1
Name: tmerge
Version: 2.0.3
Summary: Merge transcriptome read-to-genome alignments into non-redundant transcript models.
Home-page: https://github.com/jacobwindsor/tmerge
Author: Jacob Windsor, Julien Lagarde
Author-email: me@jcbwndsr.com
License: MIT
Keywords: tmerge merge transcriptomics stringtie2 rna-seq rnaseq long-read-rna long-read transcriptome
Platform: UNKNOWN
Requires-Python: >=3
